wirepas_wpe_apt/README.md
wirepas_wpe_apt/__about__.py
wirepas_wpe_apt/__init__.py
wirepas_wpe_apt/areas_manager_utils.py
wirepas_wpe_apt/areas_websocket_manager.py
wirepas_wpe_apt/common_functions.py
wirepas_wpe_apt/constants.py
wirepas_wpe_apt/data_collector.py
wirepas_wpe_apt/element.py
wirepas_wpe_apt/playback.py
wirepas_wpe_apt/report_generator.py
wirepas_wpe_apt/requirements.txt
wirepas_wpe_apt/images/wirepas_logo.jpg
wirepas_wpe_apt/wnt_proto/__init__.py
wirepas_wpe_apt/wnt_proto/commons_pb2.py
wirepas_wpe_apt/wnt_proto/commons_pb2_grpc.py
wirepas_wpe_apt/wnt_proto/internal_pb2.py
wirepas_wpe_apt/wnt_proto/internal_pb2_grpc.py
wirepas_wpe_apt/wnt_proto/message_pb2.py
wirepas_wpe_apt/wnt_proto/message_pb2_grpc.py
wirepas_wpe_apt/wnt_proto/nanopb_pb2.py
wirepas_wpe_apt/wnt_proto/nanopb_pb2_grpc.py
wirepas_wpe_apt/wnt_proto/otap_pb2.py
wirepas_wpe_apt/wnt_proto/otap_pb2_grpc.py
wirepas_wpe_apt/wnt_proto/positioning_pb2.py
wirepas_wpe_apt/wnt_proto/positioning_pb2_grpc.py
wirepas_wpe_apt/wnt_proto/remote_api_pb2.py
wirepas_wpe_apt/wnt_proto/remote_api_pb2_grpc.py
wirepas_wpe_apt/wpe_proto/__init__.py
wirepas_wpe_apt/wpe_proto/nanopb_pb2.py
wirepas_wpe_apt/wpe_proto/nanopb_pb2_grpc.py
wirepas_wpe_apt/wpe_proto/wpe_pb2.py
wirepas_wpe_apt/wpe_proto/wpe_pb2_grpc.py
wirepas_wpe_apt-1.1.0.dist-info/LICENSE
wirepas_wpe_apt-1.1.0.dist-info/METADATA
wirepas_wpe_apt-1.1.0.dist-info/WHEEL
wirepas_wpe_apt-1.1.0.dist-info/entry_points.txt
wirepas_wpe_apt-1.1.0.dist-info/top_level.txt
wirepas_wpe_apt-1.1.0.dist-info/RECORD
