Metadata-Version: 2.1
Name: wirepas-wpe-apt
Version: 1.1.0
Summary: Tool to playback computed locations data
Author: Wirepas Ltd
Author-email: opensource@wirepas.com
License: Apache-2
Keywords: Wirepas wpe playback apt
Classifier: Development Status :: 5 - Production/Stable
Classifier: Intended Audience :: Developers
Classifier: License :: OSI Approved :: Apache Software License
Classifier: Topic :: Software Development :: Libraries
Classifier: Programming Language :: Python :: 3
License-File: LICENSE
Requires-Dist: grpcio ==1.65.4
Requires-Dist: matplotlib ==3.9.0
Requires-Dist: mpld3 ==0.5.10
Requires-Dist: paho-mqtt ==2.1.0
Requires-Dist: pandas ==2.2.2
Requires-Dist: protobuf >=5.27.3
Requires-Dist: requests ==2.32.3
Requires-Dist: typing ==3.7.4.3
Requires-Dist: websocket-client ==1.8.0
